CHANGELOG.md
LICENCE.txt
MANIFEST.in
README.md
setup.py
weigangtang_reftab/__init__.py
weigangtang_reftab.egg-info/PKG-INFO
weigangtang_reftab.egg-info/SOURCES.txt
weigangtang_reftab.egg-info/dependency_links.txt
weigangtang_reftab.egg-info/requires.txt
weigangtang_reftab.egg-info/top_level.txt