Metadata-Version: 2.1
Name: weigangtang-reftab
Version: 0.0.14
Summary: manage journal reference
Home-page: UNKNOWN
Author: Weigang (Victor) Tang
Author-email: tangw5@mcmaster.ca
License: MIT
Keywords: basic,reference manager
Platform: UNKNOWN
Classifier: Development Status :: 5 - Production/Stable
Classifier: Intended Audience :: Education
Classifier: Operating System :: OS Independent 
Classifier: License :: OSI Approved :: MIT License
Classifier: Programming Language :: Python :: 3
License-File: LICENCE.txt
